lads_opcua_client/__init__.py
lads_opcua_client/main.py
lads_opcua_client/afo/AFO_Dictionary-2025_03.csv
lads_opcua_client/afo/__init__.py
lads_opcua_client/afo/afo.py
lads_opcua_client-0.1.0.dist-info/METADATA
lads_opcua_client-0.1.0.dist-info/WHEEL
lads_opcua_client-0.1.0.dist-info/licenses/LICENSE
lads_opcua_client-0.1.0.dist-info/RECORD
