Metadata-Version: 2.4
Name: lads-opcua-client
Version: 0.1.0
Summary: A python client for LADS OPC UA Server
Project-URL: Homepage, https://github.com/opcua-lads/lads-client-py
Project-URL: Issues, https://github.com/opcua-lads/lads-client-py/issues
Author-email: "Dr. Mathias Arnold" <m.arnold@aixengineers.de>, "Dr. Ricardo Cunha" <cunha@iuta.de>, Muhammad Hamad-Ul-Hassan <hamadibrahimkhel@gmail.com>
Maintainer-email: "Dr. Mathias Arnold" <m.arnold@aixengineers.de>
License-Expression: MIT
License-File: LICENSE
Classifier: Operating System :: OS Independent
Classifier: Programming Language :: Python :: 3
Requires-Python: >=3.12
Requires-Dist: asyncua>=1.1.5
Requires-Dist: pandas>=2.2.2
Requires-Dist: typing-extensions>=4.12.2
